{
  "name": "Живёшь только дважды",
  "year": 1967,
  "runtime": 117,
  "categories": [
    "боевик",
    "приключения",
    "триллер"
  ],
  "release-date": "1967-06-12",
  "director": "Льюис Гилберт",
  "writers": [
    "Харольд Джек Блум",
    "Роальд Даль",
    "Джеффри Дженкинс",
    "Иэн Флеминг"
  ],
  "actors": [
    "Шон Коннери",
    "Акико Вакабаяси",
    "Мие Хама"
  ],
  "storyline": "Британский секретный агент 007 Джеймс Бонд прибывает в Японию, чтобы предотвратить надвигающуюся ядерную войну. Недавно похитили американский и советский космические корабли, что обострило напряжённость между сверхдержавами. Подозрение падает на японцев, но Бонд убеждается в обратном. Союзничая с местным агентом Акико и отважной девушкой Кисси, он раскрывает заговор зловещей организации СПЕКТР. Их база — секретный комплекс внутри вулкана на отдалённом острове, где лидер СПЕКТР, загадочный Блофельд, готовит финальный удар: захват ещё одной ракеты для провокации глобального конфликта. Бонд проходит суровую подготовку у ниндзя, проникает в логово врага, сражается с армией ассасинов и должен уничтожить мощный ракетоноситель, чтобы спасти мир от катастрофы."
}