{
  "name": "Темный Феникс",
  "year": 2019,
  "runtime": 114,
  "categories": [
    "боевик",
    "приключения",
    "фантастика"
  ],
  "release-date": "2019-06-05",
  "director": "Саймон Кинберг",
  "writer": [
    "Саймон Кинберг"
  ],
  "actors": [
    "Джеймс МакЭвой",
    "Майкл Фассбендер",
    "Дженнифер Лоуренс",
    "Софи Тёрнер",
    "Джессика Честейн",
    "Николас Холт",
    "Тай Шеридан",
    "Александра Шипп",
    "Эван Питерс"
  ],
  "storyline": "Во время опасной космической миссии Джин Грей подвергается воздействию мощной загадочной энергии, которая резко усиливает её телепатические и телекинетические способности до невероятных пределов. Однако эта сила начинает разрушать её психику, вызывая неконтролируемые вспышки ярости и разрушений. Люди Икс, её верные друзья и соратники, пытаются помочь Джин справиться с внутренней тьмой, но её мощь представляет угрозу для всего мира. Команда оказывается перед мучительным выбором: пожертвовать одной из своих ради спасения человечества или найти способ исцелить её. В это время появляется таинственная инопланетянка, которая манипулирует ситуацией в своих целях, усугубляя хаос и заставляя героев усомниться в своих союзниках."
}