{
  "name": "Клуб «Завтрак»",
  "year": 1985,
  "runtime": 97,
  "categories": [
    "комедия",
    "драма"
  ],
  "release-date": "1985-02-15",
  "director": "Джон Хьюз",
  "writers": [
    "Джон Хьюз"
  ],
  "actors": [
    "Эмилио Эстевес",
    "Джадд Нельсон",
    "Молли Рингуолд",
    "Пол Глисон",
    "Элли Шеди"
  ],
  "storyline": "Пятеро старшеклассников из разных социальных групп — популярная красавица, спортсмен, бунтарь, отличник и тихая аутсайдерка — попадают на субботнее наказание в школьную библиотеку. Под надзором строгого директора они сначала враждуют, обмениваясь колкостями и насмешками, подчеркивая свои различия. Но по мере дня начинают открываться: делятся семейными конфликтами, давлением родителей, страхами перед взрослой жизнью и одиночеством. Они курят марихуану, танцуют под музыку, плачут и смеются вместе, осознавая, что стереотипы обманчивы. За несколько часов рождается настоящая дружба, меняющая их взгляды на себя и окружающих. Фильм раскрывает глубину подростковых переживаний и поиск идентичности."
}