{
  "name": "Другой мир: Эволюция",
  "year": 2006,
  "runtime": 106,
  "categories": [
    "ужасы",
    "боевик",
    "фантастика",
    "фэнтези",
    "триллер",
    "драма",
    "приключения"
  ],
  "release-date": "2006-01-12",
  "director": "Лен Вайзман",
  "writer": [
    "Kevin Grevioux",
    "Danny McBride",
    "Robert Orr",
    "Len Wiseman"
  ],
  "actors": [
    "Kate Beckinsale",
    "Scott Speedman",
    "Bill Nighy",
    "Tony Curran",
    "Derek Jacobi",
    "Michael Sheen",
    "Shane Brolly",
    "Steven Mackintosh",
    "Zita Görög",
    "Brian Steele"
  ],
  "storyline": "Соблазнительная вампирша Селин и ренегат-оборотень Майкл, чья любовь противоречит многовековой вражде кланов, бегут от преследователей. Их союз рождает надежду на примирение рас, но пробуждает древние тайны. Маркус, один из первых бессмертных, одержим продолжением войны и охотится за ними, раскрывая шокирующие секреты происхождения вампиров и ликанов. Неустанно атакуемые врагами с обеих сторон, влюбленные погружаются в свое прошлое, сражаются в эпичных битвах и ищут путь к спасению, эволюционируя в борьбе за судьбу миров."
}