{
  "name": "Первый игрок, приготовься",
  "year": 2018,
  "runtime": 140,
  "categories": [
    "боевик",
    "приключения",
    "фантастика"
  ],
  "release-date": "2018-03-11",
  "director": "Стивен Спилберг",
  "writer": [
    "Зак Пенн",
    "Эрнест Клайн"
  ],
  "actors": [
    "Тай Шеридан",
    "Оливия Кук",
    "Бен Мендельсон"
  ],
  "storyline": "Создатель огромного виртуального мира OASIS умирает и публикует видео с вызовом: любой пользователь, нашедший спрятанное пасхальное яйцо, унаследует его колоссальное состояние и полный контроль над OASIS. В бедных трущобах Колумбуса живёт 18-летний Уэйд Уоттс по прозвищу Парзифал. Он первым находит зацепку — первый ключ в заброшенном доме создателя. Это запускает глобальную гонку миллионов искателей приключений. Корпорация IOI во главе с Ноланом Сорлингом охотится за яйцом, чтобы захватить OASIS и превратить его в инструмент прибыли, используя армию сотрудников-рабов. Уэйд объединяется с виртуальными друзьями — отважной Артемидой, гением Эйчем и загадочной ЭйчО. Вместе они разгадывают сложные загадки, вдохновлённые поп-культурой 1980-х, сражаются с корпоративными наёмниками и раскрывают секреты прошлого создателя в погоне за сокровищем."
}