{
  "name": "Барби",
  "year": 2023,
  "runtime": 114,
  "categories": [
    "приключения",
    "комедия",
    "фэнтези"
  ],
  "release-date": "2023-07-21",
  "director": "Грета Гервиг",
  "writers": [
    "Грета Гервиг",
    "Ноа Баумбах"
  ],
  "actors": [
    "Марго Робби",
    "Райан Гослинг",
    "Исса Рэй"
  ],
  "storyline": "В идеальном розовом мире, где все счастливы и совершенны, главная героиня переживает внезапный экзистенциальный кризис. Мысли о смерти, целлюлите и плоских ступнях заставляют её усомниться в смысле существования. Старейшины отправляют её к таинственной фигуре, способной всё исправить. Вместе с наивным спутником она попадает в реальный мир людей, полный хаоса, объективизации и гендерных стереотипов. Здесь она сталкивается с патриархальными нормами, рекламой и настоящими эмоциями. Спутник тем временем увлекается идеями доминирования мужчин. Героиня борется за возвращение домой, но постепенно осознаёт ценность неидеальности, обретает свободу самовыражения и понимает, что истинное счастье — в принятии себя и окружающего мира."
}