{
  "name": "Серебряная подкладка",
  "year": 2012,
  "runtime": 122,
  "categories": [
    "комедия",
    "драма",
    "романтика"
  ],
  "release-date": "2012-12-25",
  "director": "Дэвид О. Рассел",
  "writer": "Дэвид О. Рассел",
  "actors": [
    "Брэдли Купер",
    "Дженнифер Лоуренс",
    "Роберт Де Ниро",
    "Джеки Уивер",
    "Крис Такер"
  ],
  "storyline": "После лечения в психиатрической клинике бывший учитель Пат Солитано возвращается домой к родителям и одержим идеей вернуть свою жену Николь, несмотря на запрет суда. Его вспыльчивый характер и биполярное расстройство создают хаос в семье. Жизнь меняется, когда на вечеринке он знакомится с Тиффани — молодой вдовой, страдающей от депрессии и проблем с самоконтролем после смерти мужа. Тиффани предлагает сделку: она поможет Пату связаться с женой, если он станет её партнёром на танцевальном конкурсе. Их вынужденное сотрудничество раскрывает глубокие травмы друг друга: Пат борется с гневом и иллюзиями, Тиффани — с горем и одиночеством. Поддержка эксцентричных родителей Пата и неожиданные друзья добавляют юмора и тепла. Через танцы, ссоры и откровения герои учатся принимать себя, находить радость в хаосе и открываться настоящим чувствам, доказывая, что даже в самых тёмных облаках есть серебро."
}